test.py
math_sequence/__init__.py
math_sequence/math_sequence.py
math_sequence-0.0.2.dist-info/LICENSE
math_sequence-0.0.2.dist-info/METADATA
math_sequence-0.0.2.dist-info/WHEEL
math_sequence-0.0.2.dist-info/top_level.txt
math_sequence-0.0.2.dist-info/RECORD
